libdlf/__init__.py
libdlf/fourier.py
libdlf/hankel.py
libdlf/lib/LICENSE
libdlf/lib/Fourier/fourier_grayver_50_2021_sin.npz
libdlf/lib/Fourier/fourier_key_101_2012_sincos.npz
libdlf/lib/Fourier/fourier_key_201_2012_sincos.npz
libdlf/lib/Fourier/fourier_key_241_2009_sincos.npz
libdlf/lib/Fourier/fourier_key_601_2009_sincos.npz
libdlf/lib/Fourier/fourier_key_81_2009_sincos.npz
libdlf/lib/Fourier/fourier_wer_101_2020a_sincos.npz
libdlf/lib/Fourier/fourier_wer_101_2020b_sincos.npz
libdlf/lib/Fourier/fourier_wer_201_2018_sincos.npz
libdlf/lib/Hankel/hankel_anderson_801_1982_j0j1.npz
libdlf/lib/Hankel/hankel_gupt_120_1997_j0.npz
libdlf/lib/Hankel/hankel_gupt_140_1997_j1.npz
libdlf/lib/Hankel/hankel_gupt_47_1997_j1.npz
libdlf/lib/Hankel/hankel_gupt_61_1997_j0.npz
libdlf/lib/Hankel/hankel_key_101_2009_j0j1.npz
libdlf/lib/Hankel/hankel_key_101_2012_j0j1.npz
libdlf/lib/Hankel/hankel_key_201_2009_j0j1.npz
libdlf/lib/Hankel/hankel_key_201_2012_j0j1.npz
libdlf/lib/Hankel/hankel_key_401_2009_j0j1.npz
libdlf/lib/Hankel/hankel_key_51_2012_j0j1.npz
libdlf/lib/Hankel/hankel_kong_121_2007_j0j1.npz
libdlf/lib/Hankel/hankel_kong_241_2007_j0j1.npz
libdlf/lib/Hankel/hankel_kong_61_2007b_j0j1.npz
libdlf/lib/Hankel/hankel_wer_2001_2018_j0j1.npz
libdlf/lib/Hankel/hankel_wer_201_2018_j0j1.npz
libdlf-0.3.0.dist-info/LICENSE
libdlf-0.3.0.dist-info/METADATA
libdlf-0.3.0.dist-info/WHEEL
libdlf-0.3.0.dist-info/top_level.txt
libdlf-0.3.0.dist-info/RECORD
